sentecon/__init__.py
sentecon/core.py
sentecon/data/EmpathVocab_centroids_Empath_all-MiniLM-L6-v2.csv
sentecon/data/EmpathVocab_centroids_Empath_all-mpnet-base-v2.csv
sentecon/data/LIWCVocab_centroids_LIWC_all-MiniLM-L6-v2.csv
sentecon/data/LIWCVocab_centroids_LIWC_all-distilroberta-v1.csv
sentecon/data/LIWCVocab_centroids_LIWC_all-mpnet-base-v2.csv
sentecon/data/LIWCVocab_centroids_LIWC_bert-base-uncased.csv
sentecon/data/LIWCVocab_centroids_LIWC_roberta-base.csv
sentecon/data/empath_vocab.csv
sentecon/data/liwc_vocab.csv
sentecon-0.1.9.dist-info/METADATA
sentecon-0.1.9.dist-info/WHEEL
sentecon-0.1.9.dist-info/top_level.txt
sentecon-0.1.9.dist-info/RECORD
